Workbook

Sheet Executive Summary
A1: Nisol Discovery Module — Enterprise AI Capabilities Assessment
A2: Baseline Assessment Profile: Low AI Maturity Target (SME IT Services)
A4: Company Profile Overview
A5: Company Name: | B5: Novatech Systems Ltd. | D5: Headquarters: | E5: Pune, India
A6: Company Size: | B6: 35 Employees | D6: Primary Domain: | E6: Custom Web & Mobile IT Services
A7: Annual Revenue: | B7: ~USD $3,500,000 ARR | D7: Target Maturity: | E7: Low / Early-Stage AI Readiness
A8: Current Tech Stack: | B8: PHP/Node.js, MySQL, Manual EC2, Excel Ops | D8: Assessment Date: | E8: July 2026
A9: Email: | B9: jayashriraut369@gmail.com
A11: Capability Domain Maturity Summary
A12: Section / Capability Domain | B12: Questions Evaluated | C12: Avg Maturity Rating (1-5) | D12: Maturity Level | E12: Nisol Studio Strategic Intervention
A13: Leadership & Strategy | B13: 5 | C13: =AVERAGEIF('Nisol Discovery Assessment'!$B$2:$B$63, A13, 'Nisol Discovery Assessment'!$E$2:$E$63) -> #DIV/0! | D13: =IF(C13>=4.5,"5-Optimized",IF(C13>=3.5,"4-Managed",IF(C13>=2.5,"3-Defined",IF(C13>=1.5,"2-Repeatable","1-Initial")))) -> #DIV/0! | E13: Define Pragmatic AI Policy, Executive Strategy & Dedicated R&D Budget
A14: IT / Technology | B14: 5 | C14: =AVERAGEIF('Nisol Discovery Assessment'!$B$2:$B$63, A14, 'Nisol Discovery Assessment'!$E$2:$E$63) -> #DIV/0! | D14: =IF(C14>=4.5,"5-Optimized",IF(C14>=3.5,"4-Managed",IF(C14>=2.5,"3-Defined",IF(C14>=1.5,"2-Repeatable","1-Initial")))) -> #DIV/0! | E14: Modernize CI/CD Pipelines & Introduce AI-Assisted Developer Coding Copilots
A15: Data & Analytics | B15: 5 | C15: =AVERAGEIF('Nisol Discovery Assessment'!$B$2:$B$63, A15, 'Nisol Discovery Assessment'!$E$2:$E$63) -> #DIV/0! | D15: =IF(C15>=4.5,"5-Optimized",IF(C15>=3.5,"4-Managed",IF(C15>=2.5,"3-Defined",IF(C15>=1.5,"2-Repeatable","1-Initial")))) -> #DIV/0! | E15: Centralize Siloed Databases & Build Automated Data Quality Checks
A16: Security & Compliance | B16: 5 | C16: =AVERAGEIF('Nisol Discovery Assessment'!$B$2:$B$63, A16, 'Nisol Discovery Assessment'!$E$2:$E$63) -> #DIV/0! | D16: =IF(C16>=4.5,"5-Optimized",IF(C16>=3.5,"4-Managed",IF(C16>=2.5,"3-Defined",IF(C16>=1.5,"2-Repeatable","1-Initial")))) -> #DIV/0! | E16: Establish Formal Security Guidelines, Access Controls & Patching SOPs
A17: Customer Service | B17: 4 | C17: =AVERAGEIF('Nisol Discovery Assessment'!$B$2:$B$63, A17, 'Nisol Discovery Assessment'!$E$2:$E$63) -> #DIV/0! | D17: =IF(C17>=4.5,"5-Optimized",IF(C17>=3.5,"4-Managed",IF(C17>=2.5,"3-Defined",IF(C17>=1.5,"2-Repeatable","1-Initial")))) -> #DIV/0! | E17: Deploy Knowledge Base & AI Chatbot Copilot for Client Support Ticket Automation
A18: Sales | B18: 4 | C18: =AVERAGEIF('Nisol Discovery Assessment'!$B$2:$B$63, A18, 'Nisol Discovery Assessment'!$E$2:$E$63) -> #DIV/0! | D18: =IF(C18>=4.5,"5-Optimized",IF(C18>=3.5,"4-Managed",IF(C18>=2.5,"3-Defined",IF(C18>=1.5,"2-Repeatable","1-Initial")))) -> #DIV/0! | E18: Implement Automated Proposal Templates & CRM Lead Scoring
A19: Marketing | B19: 4 | C19: =AVERAGEIF('Nisol Discovery Assessment'!$B$2:$B$63, A19, 'Nisol Discovery Assessment'!$E$2:$E$63) -> #DIV/0! | D19: =IF(C19>=4.5,"5-Optimized",IF(C19>=3.5,"4-Managed",IF(C19>=2.5,"3-Defined",IF(C19>=1.5,"2-Repeatable","1-Initial")))) -> #DIV/0! | E19: Automate Content Creation & Basic Digital Campaign Tracking
A20: Operations & Supply Chain | B20: 4 | C20: =AVERAGEIF('Nisol Discovery Assessment'!$B$2:$B$63, A20, 'Nisol Discovery Assessment'!$E$2:$E$63) -> #DIV/0! | D20: =IF(C20>=4.5,"5-Optimized",IF(C20>=3.5,"4-Managed",IF(C20>=2.5,"3-Defined",IF(C20>=1.5,"2-Repeatable","1-Initial")))) -> #DIV/0! | E20: Replace Excel Ops with Digital Resource Management & Capacity Dashboards
A21: Finance | B21: 4 | C21: =AVERAGEIF('Nisol Discovery Assessment'!$B$2:$B$63, A21, 'Nisol Discovery Assessment'!$E$2:$E$63) -> #DIV/0! | D21: =IF(C21>=4.5,"5-Optimized",IF(C21>=3.5,"4-Managed",IF(C21>=2.5,"3-Defined",IF(C21>=1.5,"2-Repeatable","1-Initial")))) -> #DIV/0! | E21: Automate Accounts Payable Data Entry & Financial Close Workflows
A22: HR | B22: 4 | C22: =AVERAGEIF('Nisol Discovery Assessment'!$B$2:$B$63, A22, 'Nisol Discovery Assessment'!$E$2:$E$63) -> #DIV/0! | D22: =IF(C22>=4.5,"5-Optimized",IF(C22>=3.5,"4-Managed",IF(C22>=2.5,"3-Defined",IF(C22>=1.5,"2-Repeatable","1-Initial")))) -> #DIV/0! | E22: Implement ATS Candidate Screening & Digital Employee Onboarding Portal
A23: Procurement | B23: 3 | C23: =AVERAGEIF('Nisol Discovery Assessment'!$B$2:$B$63, A23, 'Nisol Discovery Assessment'!$E$2:$E$63) -> #DIV/0! | D23: =IF(C23>=4.5,"5-Optimized",IF(C23>=3.5,"4-Managed",IF(C23>=2.5,"3-Defined",IF(C23>=1.5,"2-Repeatable","1-Initial")))) -> #DIV/0! | E23: Establish Central SaaS Vendor Registry & Renewal Alerts
A24: Legal | B24: 3 | C24: =AVERAGEIF('Nisol Discovery Assessment'!$B$2:$B$63, A24, 'Nisol Discovery Assessment'!$E$2:$E$63) -> #DIV/0! | D24: =IF(C24>=4.5,"5-Optimized",IF(C24>=3.5,"4-Managed",IF(C24>=2.5,"3-Defined",IF(C24>=1.5,"2-Repeatable","1-Initial")))) -> #DIV/0! | E24: Standardize NDA/MSA Templates & Deploy Automated Contract Review
... A27: Culture & Change | B27: 6 | C27: =AVERAGEIF('Nisol Discovery Assessment'!$B$2:$B$63, A27, 'Nisol Discovery Assessment'!$E$2:$E$63) -> #DIV/0! | D27: =IF(C27>=4.5,"5-Optimized",IF(C27>=3.5,"4-Managed",IF(C27>=2.5,"3-Defined",IF(C27>=1.5,"2-Repeatable","1-Initial")))) -> #DIV/0! | E27: Conduct AI Fundamentals & Prompting Training across Engineering Teams
A28: OVERALL ENTERPRISE AVERAGE | B28: =SUM(B13:B27) -> 62 | C28: =AVERAGE('Nisol Discovery Assessment'!$E$2:$E$63) -> #DIV/0! | D28: =IF(C28>=4.5,"5-Optimized",IF(C28>=3.5,"4-Managed",IF(C28>=2.5,"3-Defined",IF(C28>=1.5,"2-Repeatable","1-Initial")))) -> #DIV/0! | E28: High Growth Potential for Nisol Discovery & Studio Onboarding

Sheet Nisol Discovery Assessment

Sheet Nisol Discovery Assessment1
A1: Q# | B1: Section (Capability) | C1: Question Text | D1: Simulated Answer (Novatech Systems) | E1: Maturity Score Rating (1-5) | F1: Tip / Discussion Guidance | G1: Triggered Patterns / Nisol Modules
A2: 1 | B2: Leadership & Strategy | C2: What is the organization's top-level strategic vision for AI over the next 3 years? | D2: We do not have a formal 3-year AI strategy. Individual developers experiment with ChatGPT, but there is no top-down roadmap or dedicated AI budget. | E2: 1 | F2: Look for specifics: Is there a formal AI roadmap? Is AI mentioned in the annual report? Who is driving it—CEO, CTO, or a dedicated CAIO? | G2: ["AI Strategy Advisor","Innovation Portfolio Manager"]
A3: 2 | B3: Leadership & Strategy | C3: Who holds the ultimate decision-making authority and budget for AI investments? | D3: There is no dedicated AI budget. Any ad-hoc tool purchase (like GitHub Copilot) is approved on a case-by-case basis by the CTO. | E3: 1 | F3: Identify if this is the CEO, CTO, CIO, or a dedicated CAIO. Check if budget is centralized (one pool) or distributed across departments. | G3: ["Governance Framework Setup","Executive Dashboard"]
A4: 3 | B4: Leadership & Strategy | C4: How does the organization currently measure the success of technology or digital transformation initiatives? | D4: We measure digital initiatives purely on immediate project margins and billable client hours. We don't track tech transformation metrics systematically. | E4: 2 | F4: Probe for specific KPIs: ROI, time-to-market, efficiency gains, cost savings, or user adoption rates. Are these tracked systematically? | G4: ["Transformation KPI Tracker","Value Realization Office"]
A5: 4 | B5: Leadership & Strategy | C5: Has the organization undergone any major digital transformations in the last 3 years, and if so, what were the outcomes? | D5: We migrated a few client workloads to AWS EC2 over the last 2 years, but the process was manual and suffered from budget overruns and scope creep. | E5: 2 | F5: Understand their change appetite. Did they succeed? Fail? What were the cultural impacts? This reveals their readiness for AI-led change. | G5: ["Change Management Predictor","Legacy Migration Planner"]
A6: 5 | B6: Leadership & Strategy | C6: Is there a formal AI ethics, governance, or responsible AI policy currently in place? | D6: No formal AI ethics or governance policy exists. Engineers use public AI tools without official guidelines on data privacy or code IP risks. | E6: 1 | F6: Ask about responsible AI, bias testing, transparency requirements, and who oversees ethical AI usage. | G6: ["AI Governance Framework","Bias Detection Suite"]
A7: 6 | B7: IT / Technology | C7: What is the current state of your cloud infrastructure (On-prem, Hybrid, Cloud-native)? | D7: Hybrid/Legacy infrastructure. Most client projects run on virtual machines or basic cloud instances with substantial manual server configuration. | E7: 2 | F7: Assess maturity: Are they lifting-and-shifting legacy apps, or building cloud-native microservices? Do they use containers (Docker/K8s)? | G7: ["Cloud Optimization Agent","Application Modernization Planner"]
A8: 7 | B8: IT / Technology | C8: How mature is your API ecosystem and system integration capability? | D8: Basic REST APIs exist for client apps, but integration across internal platforms is fragmented and handled via ad-hoc point-to-point scripts. | E8: 2 | F8: Do they have an API gateway? Are systems tightly coupled (point-to-point) or loosely coupled (event-driven)? | G8: ["API Discovery & Governance","Integration Accelerator"]
A9: 8 | B9: IT / Technology | C9: What does your current software development lifecycle (SDLC) and DevOps velocity look like? | D9: SDLC relies on manual testing and semi-automated deployments. Deployments happen bi-weekly or monthly with frequent hotfixes required. | E9: 2 | F9: Probe for deployment frequency, lead time for changes, mean time to recovery (MTTR). Do they practice CI/CD? | G9: ["DevOps Assistant","CI/CD Pipeline Optimizer"]
A10: 9 | B10: IT / Technology | C10: What are the top 3 legacy systems or technical debts that are currently constraining your business? | D10: 1) Legacy monolithic client databases, 2) Heavy manual QA regression testing, 3) Lack of standardized CI/CD pipelines across project teams. | E10: 2 | F10: Identify mainframe, outdated ERPs, or custom monolithic code that hinders AI adoption and integration. | G10: ["Legacy Modernization Copilot","Technical Debt Analyzer"]
A11: 10 | B11: IT / Technology | C11: How do you currently manage vendor lock-in risk for your core technology platforms? | D11: We don't actively manage vendor lock-in; we build on whichever cloud platform the client requests without abstracting infrastructure layers. | E11: 2 | F11: Are there open-source alternatives? Are their contracts flexible? Do they have a multi-cloud or hybrid strategy? | G11: ["Vendor Risk Intelligence","Multi-Cloud Strategy Planner"]
A12: 11 | B12: Data & Analytics | C12: How do you currently handle data quality monitoring? Who is responsible, and what tools are used? | D12: Data quality is checked manually when errors or client bug reports occur. No automated monitoring tools or dedicated roles exist. | E12: 1 | F12: Probe: Is it proactive (automated) or reactive (manual checks)? Do they have data stewards? Are there data quality SLAs? | G12: ["Data Quality Monitor","Data Profiling Agent"]
A13: 12 | B13: Data & Analytics | C13: Is there a centralized data warehouse/lake, or are systems siloed? | D13: Data is heavily siloed across separate PostgreSQL/MySQL databases, spreadsheets, and individual client project repositories. | E13: 1 | F13: Determine the existence of a Single Source of Truth (SSOT). Are data pipelines ETL/ELT? Do they use tools like Snowflake, BigQuery, or Databricks? | G13: ["Data Fabric Architect","Data Lakehouse Builder"]
... A63: 62 | B63: Culture & Change | C63: Is there a clear internal communications channel for upcoming tech changes? | D63: Internal communications occur via ad-hoc Slack messages; no formal newsletter or tech update channel exists. | E63: 2 | F63: Crucial for managing digital transformation. Do they have an internal comms plan for major tech rollouts? | G63: ["Internal Comms AI","Digital Change Agent"]

Sheet Nisol Studio Roadmap
A1: Nisol Studio — AI Transformation Roadmap for Novatech Systems
A2: Phased AI Onboarding & Capability Enhancement Path
A3: Priority Phase | B3: Capability Domain | C3: Maturity Baseline | D3: Nisol Studio AI Module / Agent | E3: Target Outcome & KPI | F3: Estimated Timeline
A4: Phase 1: Foundation & Quick Wins | B4: Knowledge & SOPs | C4: Maturity: 1.0 (Initial) | D4: Nisol RAG Knowledge Wiki Agent | E4: Centralize scattered Google Docs & SOPs into an interactive developer search agent. | F4: Month 1
A5: Phase 1: Foundation & Quick Wins | B5: Sales & Proposal Scoping | C5: Maturity: 2.0 (Repeatable) | D5: Nisol Smart Proposal & SOW Generator | E5: Reduce proposal generation time from 5 days to 3 hours using structured client scope templates. | F5: Month 1 - 2
A6: Phase 1: Foundation & Quick Wins | B6: Leadership & AI Governance | C6: Maturity: 1.2 (Initial) | D6: Nisol AI Policy & Sandbox Manager | E6: Establish clear employee AI guidelines and secure internal LLM sandboxes. | F6: Month 2
A7: Phase 2: Core Delivery Efficiency | B7: IT & Code Quality | C7: Maturity: 2.0 (Repeatable) | D7: Nisol DevCopilot & Testing Agent | E7: Introduce AI coding assistants and automated unit testing to decrease delivery bugs by 30%. | F7: Month 2 - 4
A8: Phase 2: Core Delivery Efficiency | B8: Project Management | C8: Maturity: 1.7 (Initial) | D8: Nisol PM Status & Sprint Summarizer | E8: Automate weekly client status emails and Jira/Slack summary digests. | F8: Month 3 - 5
A9: Phase 2: Core Delivery Efficiency | B9: Customer Support | C9: Maturity: 1.8 (Initial) | D9: Nisol Support Ticket & Knowledge Copilot | E9: Auto-categorize client tickets and suggest resolution steps for support engineers. | F9: Month 4 - 6
A10: Phase 3: Operations & Scale | B10: Operations & Bench Ops | C10: Maturity: 1.8 (Initial) | D10: Nisol Resource Allocation Agent | E10: Replace Excel bench tracking with dynamic developer allocation and utilization tracking. | F10: Month 5 - 7
A11: Phase 3: Operations & Scale | B11: Legal & Contracts | C11: Maturity: 1.3 (Initial) | D11: Nisol Contract Review Agent | E11: Flag high-risk liability/IP clauses in client MSAs before founder review. | F11: Month 6 - 8
A12: Phase 3: Operations & Scale | B12: Finance & Invoicing | C12: Maturity: 2.0 (Repeatable) | D12: Nisol AP & Invoice Matching Agent | E12: Automate invoice extraction and reduce monthly financial close from 12 to 3 days. | F12: Month 7 - 9
