Workbook

Sheet Executive Summary
A1: Nisol Discovery Module — Enterprise AI Capabilities Assessment
A2: Simulated Organization Profile & AI Maturity Scoring
A4: Company Profile Overview
A5: Company Name: | B5: ApexTech Innovations Inc. | D5: Headquarters: | E5: Pune, India (Global Operations)
A6: Company Size: | B6: 50 Employees | D6: Primary Domain: | E6: Enterprise IT, Cloud & SaaS Engineering
A7: Annual Revenue: | B7: ~USD $10,000,000 ARR | D7: Assessment Target: | E7: Nisol Discovery & Studio AI Onboarding
A8: Current Tech Stack: | B8: AWS/GCP, Docker/K8s, Python, React, Snowflake | D8: Assessment Date: | E8: July 2026
A10: Capability Domain Maturity Summary
A11: Section / Capability Domain | B11: Questions Evaluated | C11: Avg Maturity Rating (1-5) | D11: Maturity Level | E11: Nisol Studio Strategic Focus
A12: Leadership & Strategy | B12: 5 | C12: =AVERAGEIF('Nisol Discovery Assessment'!$B$2:$B$63, A12, 'Nisol Discovery Assessment'!$E$2:$E$63) | D12: =IF(C12>=4.5,"5-Optimized",IF(C12>=3.5,"4-Managed",IF(C12>=2.5,"3-Defined",IF(C12>=1.5,"2-Repeatable","1-Initial")))) | E12: Establish AI Governance Frameworks & ROI Analytics Dashboards
A13: IT / Technology | B13: 5 | C13: =AVERAGEIF('Nisol Discovery Assessment'!$B$2:$B$63, A13, 'Nisol Discovery Assessment'!$E$2:$E$63) | D13: =IF(C13>=4.5,"5-Optimized",IF(C13>=3.5,"4-Managed",IF(C13>=2.5,"3-Defined",IF(C13>=1.5,"2-Repeatable","1-Initial")))) | E13: Deploy Agentic SDLC, Automated Code Review & Legacy Refactoring
A14: Data & Analytics | B14: 5 | C14: =AVERAGEIF('Nisol Discovery Assessment'!$B$2:$B$63, A14, 'Nisol Discovery Assessment'!$E$2:$E$63) | D14: =IF(C14>=4.5,"5-Optimized",IF(C14>=3.5,"4-Managed",IF(C14>=2.5,"3-Defined",IF(C14>=1.5,"2-Repeatable","1-Initial")))) | E14: Implement Automated Data Quality Pipelines & RAG Knowledge Graphs
A15: Security & Compliance | B15: 5 | C15: =AVERAGEIF('Nisol Discovery Assessment'!$B$2:$B$63, A15, 'Nisol Discovery Assessment'!$E$2:$E$63) | D15: =IF(C15>=4.5,"5-Optimized",IF(C15>=3.5,"4-Managed",IF(C15>=2.5,"3-Defined",IF(C15>=1.5,"2-Repeatable","1-Initial")))) | E15: Automate SOC2 / Compliance Monitoring & AI Threat Detection
A16: Customer Service | B16: 4 | C16: =AVERAGEIF('Nisol Discovery Assessment'!$B$2:$B$63, A16, 'Nisol Discovery Assessment'!$E$2:$E$63) | D16: =IF(C16>=4.5,"5-Optimized",IF(C16>=3.5,"4-Managed",IF(C16>=2.5,"3-Defined",IF(C16>=1.5,"2-Repeatable","1-Initial")))) | E16: Integrate AI Support Copilot & Self-Service Knowledge Agents
A17: Sales | B17: 4 | C17: =AVERAGEIF('Nisol Discovery Assessment'!$B$2:$B$63, A17, 'Nisol Discovery Assessment'!$E$2:$E$63) | D17: =IF(C17>=4.5,"5-Optimized",IF(C17>=3.5,"4-Managed",IF(C17>=2.5,"3-Defined",IF(C17>=1.5,"2-Repeatable","1-Initial")))) | E17: Deploy AI Proposal Generator & Automated Lead Scoring Agents
A18: Marketing | B18: 4 | C18: =AVERAGEIF('Nisol Discovery Assessment'!$B$2:$B$63, A18, 'Nisol Discovery Assessment'!$E$2:$E$63) | D18: =IF(C18>=4.5,"5-Optimized",IF(C18>=3.5,"4-Managed",IF(C18>=2.5,"3-Defined",IF(C18>=1.5,"2-Repeatable","1-Initial")))) | E18: Automate Multi-Channel Campaign Creation & SEO Analytics
A19: Operations & Supply Chain | B19: 4 | C19: =AVERAGEIF('Nisol Discovery Assessment'!$B$2:$B$63, A19, 'Nisol Discovery Assessment'!$E$2:$E$63) | D19: =IF(C19>=4.5,"5-Optimized",IF(C19>=3.5,"4-Managed",IF(C19>=2.5,"3-Defined",IF(C19>=1.5,"2-Repeatable","1-Initial")))) | E19: Optimize Resource Capacity Allocation & Vendor Lifecycle Automation
A20: Finance | B20: 4 | C20: =AVERAGEIF('Nisol Discovery Assessment'!$B$2:$B$63, A20, 'Nisol Discovery Assessment'!$E$2:$E$63) | D20: =IF(C20>=4.5,"5-Optimized",IF(C20>=3.5,"4-Managed",IF(C20>=2.5,"3-Defined",IF(C20>=1.5,"2-Repeatable","1-Initial")))) | E20: Automate Accounts Payable Workflow & Financial FP&A Forecasting
A21: HR | B21: 4 | C21: =AVERAGEIF('Nisol Discovery Assessment'!$B$2:$B$63, A21, 'Nisol Discovery Assessment'!$E$2:$E$63) | D21: =IF(C21>=4.5,"5-Optimized",IF(C21>=3.5,"4-Managed",IF(C21>=2.5,"3-Defined",IF(C21>=1.5,"2-Repeatable","1-Initial")))) | E21: Deploy AI Resume Screening, Onboarding Copilots & Talent Analytics
A22: Procurement | B22: 3 | C22: =AVERAGEIF('Nisol Discovery Assessment'!$B$2:$B$63, A22, 'Nisol Discovery Assessment'!$E$2:$E$63) | D22: =IF(C22>=4.5,"5-Optimized",IF(C22>=3.5,"4-Managed",IF(C22>=2.5,"3-Defined",IF(C22>=1.5,"2-Repeatable","1-Initial")))) | E22: Automate Vendor Risk Evaluation & Contract SLA Benchmark
A23: Legal | B23: 3 | C23: =AVERAGEIF('Nisol Discovery Assessment'!$B$2:$B$63, A23, 'Nisol Discovery Assessment'!$E$2:$E$63) | D23: =IF(C23>=4.5,"5-Optimized",IF(C23>=3.5,"4-Managed",IF(C23>=2.5,"3-Defined",IF(C23>=1.5,"2-Repeatable","1-Initial")))) | E23: Deploy Contract Redlining & NDA Automated Review Agents
... A26: Culture & Change | B26: 6 | C26: =AVERAGEIF('Nisol Discovery Assessment'!$B$2:$B$63, A26, 'Nisol Discovery Assessment'!$E$2:$E$63) | D26: =IF(C26>=4.5,"5-Optimized",IF(C26>=3.5,"4-Managed",IF(C26>=2.5,"3-Defined",IF(C26>=1.5,"2-Repeatable","1-Initial")))) | E26: Launch Internal AI Literacy Programs & Innovation Sandboxes
A27: OVERALL ENTERPRISE AVERAGE | B27: =SUM(B12:B26) | C27: =AVERAGE('Nisol Discovery Assessment'!$E$2:$E$63) | D27: =IF(C27>=4.5,"5-Optimized",IF(C27>=3.5,"4-Managed",IF(C27>=2.5,"3-Defined",IF(C27>=1.5,"2-Repeatable","1-Initial")))) | E27: Target Profile: High Readiness for Nisol Studio Deployment

Sheet Nisol Discovery Assessment
A1: Q# | B1: Section (Capability) | C1: Question Text | D1: Simulated Answer (ApexTech Innovations) | E1: Maturity Score Rating (1-5) | F1: Tip / Discussion Guidance | G1: Triggered Patterns / Nisol Modules
A2: 1 | B2: Leadership & Strategy | C2: What is the organization's top-level strategic vision for AI over the next 3 years? | D2: Our strategic vision is to transform into an 'AI-First' software engineering firm within 3 years. We plan to embed GenAI and Agentic AI into our client project delivery, internal governance, and dev workflows to increase velocity by 40%. | E2: 4 | F2: Look for specifics: Is there a formal AI roadmap? Is AI mentioned in the annual report? Who is driving it—CEO, CTO, or a dedicated CAIO? | G2: ["AI Strategy Advisor","Innovation Portfolio Manager"]
A3: 2 | B3: Leadership & Strategy | C3: Who holds the ultimate decision-making authority and budget for AI investments? | D3: The ultimate decision-making authority and budget reside jointly with the CEO and CTO. We have allocated a dedicated 8% of annual revenue (~$800K) specifically for internal R&D, AI tooling, and pilot projects. | E3: 4 | F3: Identify if this is the CEO, CTO, CIO, or a dedicated CAIO. Check if budget is centralized (one pool) or distributed across departments. | G3: ["Governance Framework Setup","Executive Dashboard"]
A4: 3 | B4: Leadership & Strategy | C4: How does the organization currently measure the success of technology or digital transformation initiatives? | D4: We track digital transformation and R&D ROI using strict KPIs: Client Delivery Velocity (sprint burn-down efficiency), Margin Improvement (cost per project), Time-to-Market for custom modules, and Client CSAT/NPS scores. | E4: 4 | F4: Probe for specific KPIs: ROI, time-to-market, efficiency gains, cost savings, or user adoption rates. Are these tracked systematically? | G4: ["Transformation KPI Tracker","Value Realization Office"]
A5: 4 | B5: Leadership & Strategy | C5: Has the organization undergone any major digital transformations in the last 3 years, and if so, what were the outcomes? | D5: Over the last 3 years, we transitioned from legacy monolithic client builds to 100% cloud-native serverless and microservices architectures. Outcomes included a 35% reduction in deployment bugs and 25% higher client satisfaction. | E5: 4 | F5: Understand their change appetite. Did they succeed? Fail? What were the cultural impacts? This reveals their readiness for AI-led change. | G5: ["Change Management Predictor","Legacy Migration Planner"]
A6: 5 | B6: Leadership & Strategy | C6: Is there a formal AI ethics, governance, or responsible AI policy currently in place? | D6: We maintain an internal Responsible AI & Data Ethics Guidelines document covering client data privacy, code licensing, IP ownership, and mandatory human-in-the-loop validation for all AI-generated code and deliverables. | E6: 3 | F6: Ask about responsible AI, bias testing, transparency requirements, and who oversees ethical AI usage. | G6: ["AI Governance Framework","Bias Detection Suite"]
A7: 6 | B7: IT / Technology | C7: What is the current state of your cloud infrastructure (On-prem, Hybrid, Cloud-native)? | D7: We are 100% cloud-native, running AWS and GCP infrastructure with automated Infrastructure-as-Code (Terraform) and containerized orchestration via Kubernetes. | E7: 5 | F7: Assess maturity: Are they lifting-and-shifting legacy apps, or building cloud-native microservices? Do they use containers (Docker/K8s)? | G7: ["Cloud Optimization Agent","Application Modernization Planner"]
A8: 7 | B8: IT / Technology | C8: How mature is your API ecosystem and system integration capability? | D8: Highly mature. We build and maintain RESTful and GraphQL APIs for all client solutions and internal microservices. Internal services communicate via event-driven messaging (Kafka/RabbitMQ). | E8: 4 | F8: Do they have an API gateway? Are systems tightly coupled (point-to-point) or loosely coupled (event-driven)? | G8: ["API Discovery & Governance","Integration Accelerator"]
A9: 8 | B9: IT / Technology | C9: What does your current software development lifecycle (SDLC) and DevOps velocity look like? | D9: We operate on 2-week Agile sprints with fully automated CI/CD pipelines (GitHub Actions / GitLab CI). Average deployment frequency is multiple times per day with automated test coverage over 80%. | E9: 5 | F9: Probe for deployment frequency, lead time for changes, mean time to recovery (MTTR). Do they practice CI/CD? | G9: ["DevOps Assistant","CI/CD Pipeline Optimizer"]
A10: 9 | B10: IT / Technology | C10: What are the top 3 legacy systems or technical debts that are currently constraining your business? | D10: 1) Legacy client codebase integration adapters. 2) Manual QA regression overhead for older enterprise builds. 3) Disparate internal reporting systems requiring custom data pipelines. | E10: 3 | F10: Identify mainframe, outdated ERPs, or custom monolithic code that hinders AI adoption and integration. | G10: ["Legacy Modernization Copilot","Technical Debt Analyzer"]
A11: 10 | B11: IT / Technology | C11: How do you currently manage vendor lock-in risk for your core technology platforms? | D11: We mandate cloud-agnostic architectures (Docker, Kubernetes, Terraform) and open-source frameworks where possible. Multi-cloud deployment capabilities prevent reliance on any single cloud vendor. | E11: 4 | F11: Are there open-source alternatives? Are their contracts flexible? Do they have a multi-cloud or hybrid strategy? | G11: ["Vendor Risk Intelligence","Multi-Cloud Strategy Planner"]
A12: 11 | B12: Data & Analytics | C12: How do you currently handle data quality monitoring? Who is responsible, and what tools are used? | D12: Data quality monitoring is managed by our Data & Cloud Practice leads. We use automated validation frameworks (Great Expectations) and schema enforcement in our data pipelines. | E12: 3 | F12: Probe: Is it proactive (automated) or reactive (manual checks)? Do they have data stewards? Are there data quality SLAs? | G12: ["Data Quality Monitor","Data Profiling Agent"]
A13: 12 | B13: Data & Analytics | C13: Is there a centralized data warehouse/lake, or are systems siloed? | D13: We maintain a centralized Snowflake data warehouse integrated with PostgreSQL databases and internal telemetry feeds, eliminating siloed data repositories. | E13: 4 | F13: Determine the existence of a Single Source of Truth (SSOT). Are data pipelines ETL/ELT? Do they use tools like Snowflake, BigQuery, or Databricks? | G13: ["Data Fabric Architect","Data Lakehouse Builder"]
... A63: 62 | B63: Culture & Change | C63: Is there a clear internal communications channel for upcoming tech changes? | D63: Clear internal communication channels exist via weekly town halls, Slack announcements, and monthly CTO technical briefing newsletters. | E63: 4 | F63: Crucial for managing digital transformation. Do they have an internal comms plan for major tech rollouts? | G63: ["Internal Comms AI","Digital Change Agent"]

Sheet Nisol Studio Roadmap
A1: Nisol Studio — AI Implementation & Agentic Automation Roadmap
A2: Transitioning Discovery Assessment Insights into Nisol Studio Execution
A3: Priority Tier | B3: Capability Domain | C3: Maturity Baseline | D3: Nisol Studio AI Module / Agent | E3: Target Outcome & KPI | F3: Estimated Timeline
A4: Tier 1: High ROI / Quick Wins | B4: Legal | C4: Maturity: 3.0 (Defined) | D4: Nisol LegalDoc Redline Agent | E4: Automate client NDA/MSA contract review; reduce turnaround time from 3 days to 2 hours. | F4: Weeks 1 - 4
A5: Tier 1: High ROI / Quick Wins | B5: Sales & Proposals | C5: Maturity: 3.5 (Managed) | D5: Nisol ProposalGen Copilot | E5: Auto-generate technical proposals and SOWs from client RFPs using historical winning bids. | F5: Weeks 2 - 6
A6: Tier 1: High ROI / Quick Wins | B6: Project Management | C6: Maturity: 4.0 (Managed) | D6: Nisol PMO Velocity & Governance Agent | E6: Auto-generate sprint progress, meeting summaries, and risks from Jira and Slack. | F6: Weeks 3 - 8
A7: Tier 2: Core Engineering Scale | B7: IT / Technology | C7: Maturity: 4.4 (Optimized) | D7: Nisol DevCopilot & CodeRefactor Agent | E7: Automate legacy code refactoring, code reviews, and unit test generation across client pods. | F7: Weeks 5 - 12
A8: Tier 2: Core Engineering Scale | B8: Data & Analytics | C8: Maturity: 3.4 (Defined) | D8: Nisol DataQuality & RAG Knowledge Pipeline | E8: Automated data schema validation and enterprise semantic search across internal wikis. | F8: Weeks 6 - 14
A9: Tier 2: Core Engineering Scale | B9: Customer Service | C9: Maturity: 3.8 (Managed) | D9: Nisol Omnichannel Support Agent | E9: AI-first ticket categorization, SLA tracking, and auto-resolution for standard client tickets. | F9: Weeks 8 - 16
A10: Tier 3: Enterprise Transformation | B10: HR & Talent | C10: Maturity: 3.5 (Managed) | D10: Nisol Talent Sourcing & Onboarding Agent | E10: Automate resume screening against technical rubrics and personalized developer onboarding. | F10: Weeks 10 - 18
A11: Tier 3: Enterprise Transformation | B11: Finance & FP&A | C11: Maturity: 3.5 (Managed) | D11: Nisol Accounts Payable & Cash Flow Agent | E11: Automate invoice matching, vendor payout workflows, and real-time ARR forecasting. | F11: Weeks 12 - 20
A12: Tier 3: Enterprise Transformation | B12: Leadership & Culture | C12: Maturity: 3.8 (Managed) | D12: Nisol AI Governance & Innovation Dashboard | E12: Executive tracking of AI agent ROI, usage telemetry, and responsible AI compliance across squads. | F12: Continuous
